django_tasks_cloud/__init__.py
django_tasks_cloud/aws/__init__.py
django_tasks_cloud/aws/apps.py
django_tasks_cloud/aws/backends.py
django_tasks_cloud/aws/tests.py
django_tasks_cloud/azure/__init__.py
django_tasks_cloud/azure/apps.py
django_tasks_cloud/azure/backends/__init__.py
django_tasks_cloud/azure/backends/sa_queue.py
django_tasks_cloud/azure/backends/service_bus.py
django_tasks_cloud/azure/tests.py
django_tasks_cloud/base/__init__.py
django_tasks_cloud/base/admin.py
django_tasks_cloud/base/apps.py
django_tasks_cloud/base/models.py
django_tasks_cloud/base/tests.py
django_tasks_cloud/base/urls.py
django_tasks_cloud/base/views.py
django_tasks_cloud-0.2.0b1.dist-info/licenses/LICENSE
django_tasks_cloud-0.2.0b1.dist-info/WHEEL
django_tasks_cloud-0.2.0b1.dist-info/METADATA
django_tasks_cloud-0.2.0b1.dist-info/RECORD
