Metadata-Version: 2.4
Name: django-tasks-cloud
Version: 0.2.0b1
Summary: Manage long running tasks out of request-response cycle with Django's all-new `Task` back-end and AWS/Azure native-services.
Author: Developers at PaperCloud Tech
Author-email: Developers at PaperCloud Tech <developers@papercloud.tech>
License-Expression: MIT
License-File: LICENSE
Classifier: Programming Language :: Python :: 3
Classifier: Operating System :: OS Independent
Requires-Dist: django==6.0
Requires-Python: >=3.12
Project-URL: Homepage, https://github.com/papercloudtech/django-cloud-tasks
Project-URL: Issues, https://github.com/papercloudtech/django-cloud-tasks/issues
